{
  "uid": "kiosk-host-detail",
  "title": "Kiosk Host — Detail",
  "tags": [
    "kiosk",
    "lfac"
  ],
  "timezone": "",
  "schemaVersion": 39,
  "editable": true,
  "refresh": "1m",
  "links": [
    {
      "type": "dashboards",
      "title": "Kiosk dashboards",
      "tags": [
        "kiosk"
      ],
      "asDropdown": true,
      "includeVars": true,
      "keepTime": true,
      "icon": "external link",
      "targetBlank": false
    },
    {
      "type": "link",
      "title": "Visual Timeline",
      "url": "https://kiosk-timeline.xzibitapps.workers.dev/app?k=d6210121f591954d5bf4b28376e3e15576e5702f540f6117",
      "icon": "external link",
      "targetBlank": true,
      "keepTime": true,
      "includeVars": false,
      "tooltip": "Scrub-able screenshot timeline for the fleet (opens with this dashboard's time range)"
    }
  ],
  "time": {
    "from": "now-6h",
    "to": "now"
  },
  "templating": {
    "list": [
      {
        "name": "instance",
        "type": "query",
        "label": "Kiosk",
        "datasource": {
          "type": "prometheus",
          "uid": "grafanacloud-prom"
        },
        "definition": "label_values(kiosk_agent_info, instance)",
        "query": {
          "query": "label_values(kiosk_agent_info, instance)",
          "refId": "StandardVariableQuery"
        },
        "includeAll": false,
        "multi": false,
        "current": {
          "text": "LFSC-MPC2-1-1",
          "value": "LFSC-MPC2-1-1"
        },
        "refresh": 2,
        "sort": 1
      }
    ]
  },
  "panels": [
    {
      "id": 1,
      "type": "row",
      "title": "Host",
      "collapsed": false,
      "gridPos": {
        "h": 1,
        "w": 24,
        "x": 0,
        "y": 0
      }
    },
    {
      "id": 2,
      "type": "stat",
      "title": "Uptime",
      "gridPos": {
        "h": 4,
        "w": 5,
        "x": 0,
        "y": 1
      },
      "datasource": {
        "type": "prometheus",
        "uid": "grafanacloud-prom"
      },
      "targets": [
        {
          "refId": "A",
          "editorMode": "code",
          "expr": "time() - windows_system_boot_time_timestamp{instance=~\"$instance\"}",
          "instant": true
        }
      ],
      "options": {
        "reduceOptions": {
          "calcs": [
            "lastNotNull"
          ]
        },
        "colorMode": "value",
        "graphMode": "none"
      },
      "fieldConfig": {
        "defaults": {
          "unit": "s"
        }
      }
    },
    {
      "id": 3,
      "type": "stat",
      "title": "Last reboot",
      "gridPos": {
        "h": 4,
        "w": 5,
        "x": 5,
        "y": 1
      },
      "datasource": {
        "type": "prometheus",
        "uid": "grafanacloud-prom"
      },
      "targets": [
        {
          "refId": "A",
          "editorMode": "code",
          "expr": "windows_system_boot_time_timestamp{instance=~\"$instance\"} * 1000",
          "instant": true
        }
      ],
      "options": {
        "reduceOptions": {
          "calcs": [
            "lastNotNull"
          ]
        },
        "colorMode": "none",
        "graphMode": "none"
      },
      "fieldConfig": {
        "defaults": {
          "unit": "dateTimeFromNow"
        }
      }
    },
    {
      "id": 4,
      "type": "stat",
      "title": "Kiosk mode",
      "gridPos": {
        "h": 4,
        "w": 5,
        "x": 10,
        "y": 1
      },
      "datasource": {
        "type": "prometheus",
        "uid": "grafanacloud-prom"
      },
      "targets": [
        {
          "refId": "A",
          "editorMode": "code",
          "expr": "max(kiosk_mode{instance=~\"$instance\"})",
          "instant": true
        }
      ],
      "options": {
        "reduceOptions": {
          "calcs": [
            "lastNotNull"
          ]
        },
        "colorMode": "background",
        "graphMode": "none"
      },
      "fieldConfig": {
        "defaults": {
          "unit": "short",
          "mappings": [
            {
              "type": "value",
              "options": {
                "0": {
                  "text": "Off",
                  "color": "red"
                },
                "1": {
                  "text": "ON",
                  "color": "green"
                }
              }
            }
          ]
        }
      }
    },
    {
      "id": 5,
      "type": "stat",
      "title": "App up",
      "gridPos": {
        "h": 4,
        "w": 4,
        "x": 15,
        "y": 1
      },
      "datasource": {
        "type": "prometheus",
        "uid": "grafanacloud-prom"
      },
      "targets": [
        {
          "refId": "A",
          "editorMode": "code",
          "expr": "max(kiosk_app_up{instance=~\"$instance\"})",
          "instant": true
        }
      ],
      "options": {
        "reduceOptions": {
          "calcs": [
            "lastNotNull"
          ]
        },
        "colorMode": "background",
        "graphMode": "none"
      },
      "fieldConfig": {
        "defaults": {
          "unit": "short",
          "mappings": [
            {
              "type": "value",
              "options": {
                "0": {
                  "text": "DOWN",
                  "color": "red"
                },
                "1": {
                  "text": "up",
                  "color": "green"
                }
              }
            }
          ]
        }
      }
    },
    {
      "id": 6,
      "type": "stat",
      "title": "Reboot pending",
      "gridPos": {
        "h": 4,
        "w": 5,
        "x": 19,
        "y": 1
      },
      "datasource": {
        "type": "prometheus",
        "uid": "grafanacloud-prom"
      },
      "targets": [
        {
          "refId": "A",
          "editorMode": "code",
          "expr": "max(kiosk_reboot_pending{instance=~\"$instance\"})",
          "instant": true
        }
      ],
      "options": {
        "reduceOptions": {
          "calcs": [
            "lastNotNull"
          ]
        },
        "colorMode": "background",
        "graphMode": "none"
      },
      "fieldConfig": {
        "defaults": {
          "unit": "short",
          "mappings": [
            {
              "type": "value",
              "options": {
                "0": {
                  "text": "no",
                  "color": "green"
                },
                "1": {
                  "text": "YES",
                  "color": "orange"
                }
              }
            }
          ]
        }
      }
    },
    {
      "id": 7,
      "type": "gauge",
      "title": "CPU busy %",
      "gridPos": {
        "h": 6,
        "w": 6,
        "x": 0,
        "y": 5
      },
      "datasource": {
        "type": "prometheus",
        "uid": "grafanacloud-prom"
      },
      "targets": [
        {
          "refId": "A",
          "editorMode": "code",
          "expr": "100 - (avg (rate(windows_cpu_time_total{mode=\"idle\", instance=~\"$instance\"}[5m])) * 100)",
          "instant": true
        }
      ],
      "options": {
        "reduceOptions": {
          "calcs": [
            "lastNotNull"
          ]
        },
        "showThresholdLabels": false
      },
      "fieldConfig": {
        "defaults": {
          "unit": "percent",
          "min": 0,
          "max": 100,
          "thresholds": {
            "mode": "absolute",
            "steps": [
              {
                "color": "green",
                "value": null
              },
              {
                "color": "orange",
                "value": 85
              },
              {
                "color": "red",
                "value": 95
              }
            ]
          }
        }
      }
    },
    {
      "id": 8,
      "type": "gauge",
      "title": "Memory used %",
      "gridPos": {
        "h": 6,
        "w": 6,
        "x": 6,
        "y": 5
      },
      "datasource": {
        "type": "prometheus",
        "uid": "grafanacloud-prom"
      },
      "targets": [
        {
          "refId": "A",
          "editorMode": "code",
          "expr": "100 * (1 - avg(windows_memory_available_bytes{instance=~\"$instance\"}) / avg(windows_memory_physical_total_bytes{instance=~\"$instance\"}))",
          "instant": true
        }
      ],
      "options": {
        "reduceOptions": {
          "calcs": [
            "lastNotNull"
          ]
        },
        "showThresholdLabels": false
      },
      "fieldConfig": {
        "defaults": {
          "unit": "percent",
          "min": 0,
          "max": 100,
          "thresholds": {
            "mode": "absolute",
            "steps": [
              {
                "color": "green",
                "value": null
              },
              {
                "color": "orange",
                "value": 85
              },
              {
                "color": "red",
                "value": 95
              }
            ]
          }
        }
      }
    },
    {
      "id": 9,
      "type": "gauge",
      "title": "Disk free % (C:)",
      "gridPos": {
        "h": 6,
        "w": 6,
        "x": 12,
        "y": 5
      },
      "datasource": {
        "type": "prometheus",
        "uid": "grafanacloud-prom"
      },
      "targets": [
        {
          "refId": "A",
          "editorMode": "code",
          "expr": "avg(windows_logical_disk_free_bytes{volume=\"C:\", instance=~\"$instance\"}) / avg(windows_logical_disk_size_bytes{volume=\"C:\", instance=~\"$instance\"}) * 100",
          "instant": true
        }
      ],
      "options": {
        "reduceOptions": {
          "calcs": [
            "lastNotNull"
          ]
        },
        "showThresholdLabels": false
      },
      "fieldConfig": {
        "defaults": {
          "unit": "percent",
          "min": 0,
          "max": 100,
          "thresholds": {
            "mode": "absolute",
            "steps": [
              {
                "color": "red",
                "value": 10
              },
              {
                "color": "orange",
                "value": 10
              },
              {
                "color": "green",
                "value": 20
              }
            ]
          }
        }
      }
    },
    {
      "id": 10,
      "type": "gauge",
      "title": "Max temperature",
      "gridPos": {
        "h": 6,
        "w": 6,
        "x": 18,
        "y": 5
      },
      "datasource": {
        "type": "prometheus",
        "uid": "grafanacloud-prom"
      },
      "targets": [
        {
          "refId": "A",
          "editorMode": "code",
          "expr": "max(windows_thermalzone_temperature_celsius{instance=~\"$instance\"})",
          "instant": true
        }
      ],
      "options": {
        "reduceOptions": {
          "calcs": [
            "lastNotNull"
          ]
        },
        "showThresholdLabels": false
      },
      "fieldConfig": {
        "defaults": {
          "unit": "celsius",
          "min": 0,
          "max": 100,
          "thresholds": {
            "mode": "absolute",
            "steps": [
              {
                "color": "green",
                "value": null
              },
              {
                "color": "orange",
                "value": 70
              },
              {
                "color": "red",
                "value": 85
              }
            ]
          }
        }
      }
    },
    {
      "id": 11,
      "type": "row",
      "title": "Currency & updates",
      "collapsed": false,
      "gridPos": {
        "h": 1,
        "w": 24,
        "x": 0,
        "y": 11
      }
    },
    {
      "id": 12,
      "type": "table",
      "title": "Component versions (installed vs desired)",
      "gridPos": {
        "h": 9,
        "w": 12,
        "x": 0,
        "y": 12
      },
      "datasource": {
        "type": "prometheus",
        "uid": "grafanacloud-prom"
      },
      "targets": [
        {
          "refId": "A",
          "editorMode": "code",
          "format": "table",
          "instant": true,
          "expr": "kiosk_agent_component_info{instance=~\"$instance\"}"
        }
      ],
      "transformations": [
        {
          "id": "organize",
          "options": {
            "excludeByName": {
              "Time": true,
              "job": true,
              "__name__": true,
              "fleet": true,
              "host": true,
              "Value": true
            },
            "indexByName": {
              "instance": 0,
              "component": 1,
              "kind": 2,
              "installed": 3,
              "desired": 4
            }
          }
        }
      ],
      "fieldConfig": {
        "defaults": {},
        "overrides": [
          {
            "matcher": {
              "id": "byName",
              "options": "installed"
            },
            "properties": [
              {
                "id": "custom.cellOptions",
                "value": {
                  "type": "color-text"
                }
              }
            ]
          }
        ]
      }
    },
    {
      "id": 13,
      "type": "table",
      "title": "Pending Windows updates",
      "gridPos": {
        "h": 9,
        "w": 12,
        "x": 12,
        "y": 12
      },
      "datasource": {
        "type": "prometheus",
        "uid": "grafanacloud-prom"
      },
      "targets": [
        {
          "refId": "A",
          "editorMode": "code",
          "format": "table",
          "instant": true,
          "expr": "windows_update_pending_info{instance=~\"$instance\"}"
        }
      ],
      "transformations": [
        {
          "id": "organize",
          "options": {
            "excludeByName": {
              "Time": true,
              "job": true,
              "__name__": true,
              "fleet": true,
              "host": true,
              "site": true,
              "location": true,
              "environment": true,
              "instance": true,
              "Value": true,
              "id": true,
              "revision": true
            },
            "indexByName": {
              "category": 0,
              "title": 1
            }
          }
        }
      ],
      "fieldConfig": {
        "defaults": {}
      }
    },
    {
      "id": 14,
      "type": "stat",
      "title": "Last hotfix",
      "gridPos": {
        "h": 4,
        "w": 8,
        "x": 0,
        "y": 21
      },
      "datasource": {
        "type": "prometheus",
        "uid": "grafanacloud-prom"
      },
      "targets": [
        {
          "refId": "A",
          "editorMode": "code",
          "expr": "kiosk_last_hotfix_timestamp_seconds{instance=~\"$instance\"} * 1000",
          "instant": true
        }
      ],
      "options": {
        "reduceOptions": {
          "calcs": [
            "lastNotNull"
          ]
        },
        "colorMode": "none",
        "graphMode": "none"
      },
      "fieldConfig": {
        "defaults": {
          "unit": "dateTimeFromNow"
        }
      }
    },
    {
      "id": 15,
      "type": "stat",
      "title": "WU service running",
      "gridPos": {
        "h": 4,
        "w": 8,
        "x": 8,
        "y": 21
      },
      "datasource": {
        "type": "prometheus",
        "uid": "grafanacloud-prom"
      },
      "targets": [
        {
          "refId": "A",
          "editorMode": "code",
          "expr": "max(kiosk_wu_service_running{instance=~\"$instance\"})",
          "instant": true
        }
      ],
      "options": {
        "reduceOptions": {
          "calcs": [
            "lastNotNull"
          ]
        },
        "colorMode": "background",
        "graphMode": "none"
      },
      "fieldConfig": {
        "defaults": {
          "unit": "short",
          "mappings": [
            {
              "type": "value",
              "options": {
                "0": {
                  "text": "stopped",
                  "color": "orange"
                },
                "1": {
                  "text": "running",
                  "color": "green"
                }
              }
            }
          ]
        }
      }
    },
    {
      "id": 16,
      "type": "stat",
      "title": "WU service disabled",
      "gridPos": {
        "h": 4,
        "w": 8,
        "x": 16,
        "y": 21
      },
      "datasource": {
        "type": "prometheus",
        "uid": "grafanacloud-prom"
      },
      "targets": [
        {
          "refId": "A",
          "editorMode": "code",
          "expr": "max(kiosk_wu_service_disabled{instance=~\"$instance\"})",
          "instant": true
        }
      ],
      "options": {
        "reduceOptions": {
          "calcs": [
            "lastNotNull"
          ]
        },
        "colorMode": "background",
        "graphMode": "none"
      },
      "fieldConfig": {
        "defaults": {
          "unit": "short",
          "mappings": [
            {
              "type": "value",
              "options": {
                "0": {
                  "text": "no",
                  "color": "green"
                },
                "1": {
                  "text": "DISABLED",
                  "color": "orange"
                }
              }
            }
          ]
        }
      }
    },
    {
      "id": 17,
      "type": "row",
      "title": "Storage (SSD / disk health)",
      "collapsed": false,
      "gridPos": {
        "h": 1,
        "w": 24,
        "x": 0,
        "y": 25
      }
    },
    {
      "id": 18,
      "type": "bargauge",
      "title": "SSD wear %",
      "gridPos": {
        "h": 8,
        "w": 8,
        "x": 0,
        "y": 26
      },
      "datasource": {
        "type": "prometheus",
        "uid": "grafanacloud-prom"
      },
      "targets": [
        {
          "refId": "A",
          "editorMode": "code",
          "expr": "kiosk_disk_wear_percent{instance=~\"$instance\"}",
          "instant": true,
          "legendFormat": "{{model}}"
        }
      ],
      "options": {
        "displayMode": "gradient",
        "orientation": "horizontal",
        "reduceOptions": {
          "calcs": [
            "lastNotNull"
          ]
        },
        "showUnfilled": true
      },
      "fieldConfig": {
        "defaults": {
          "unit": "percent",
          "thresholds": {
            "mode": "absolute",
            "steps": [
              {
                "color": "green",
                "value": null
              },
              {
                "color": "orange",
                "value": 80
              },
              {
                "color": "red",
                "value": 90
              }
            ]
          },
          "description": "Percentage of rated write life used (higher = more worn)."
        }
      }
    },
    {
      "id": 19,
      "type": "bargauge",
      "title": "SSD temperature (°C)",
      "gridPos": {
        "h": 8,
        "w": 8,
        "x": 8,
        "y": 26
      },
      "datasource": {
        "type": "prometheus",
        "uid": "grafanacloud-prom"
      },
      "targets": [
        {
          "refId": "A",
          "editorMode": "code",
          "expr": "kiosk_disk_temperature_celsius{instance=~\"$instance\"}",
          "instant": true,
          "legendFormat": "{{model}}"
        }
      ],
      "options": {
        "displayMode": "gradient",
        "orientation": "horizontal",
        "reduceOptions": {
          "calcs": [
            "lastNotNull"
          ]
        },
        "showUnfilled": true
      },
      "fieldConfig": {
        "defaults": {
          "unit": "celsius",
          "thresholds": {
            "mode": "absolute",
            "steps": [
              {
                "color": "green",
                "value": null
              },
              {
                "color": "orange",
                "value": 60
              },
              {
                "color": "red",
                "value": 70
              }
            ]
          }
        }
      }
    },
    {
      "id": 20,
      "type": "table",
      "title": "Disks",
      "gridPos": {
        "h": 8,
        "w": 8,
        "x": 16,
        "y": 26
      },
      "datasource": {
        "type": "prometheus",
        "uid": "grafanacloud-prom"
      },
      "targets": [
        {
          "refId": "A",
          "editorMode": "code",
          "instant": true,
          "format": "table",
          "expr": "kiosk_disk_healthy{instance=~\"$instance\"}"
        }
      ],
      "transformations": [
        {
          "id": "organize",
          "options": {
            "excludeByName": {
              "Time": true,
              "job": true,
              "__name__": true,
              "fleet": true,
              "host": true,
              "site": true,
              "location": true,
              "environment": true,
              "instance": true
            },
            "renameByName": {
              "Value": "healthy"
            },
            "indexByName": {
              "disk": 0,
              "model": 1,
              "media": 2,
              "healthy": 3
            }
          }
        }
      ],
      "fieldConfig": {
        "defaults": {},
        "overrides": [
          {
            "matcher": {
              "id": "byName",
              "options": "healthy"
            },
            "properties": [
              {
                "id": "mappings",
                "value": [
                  {
                    "type": "value",
                    "options": {
                      "0": {
                        "text": "UNHEALTHY",
                        "color": "red"
                      },
                      "1": {
                        "text": "healthy",
                        "color": "green"
                      }
                    }
                  }
                ]
              },
              {
                "id": "custom.cellOptions",
                "value": {
                  "type": "color-text"
                }
              }
            ]
          }
        ]
      }
    },
    {
      "id": 21,
      "type": "timeseries",
      "title": "SSD temperature — trend",
      "gridPos": {
        "h": 6,
        "w": 24,
        "x": 0,
        "y": 34
      },
      "datasource": {
        "type": "prometheus",
        "uid": "grafanacloud-prom"
      },
      "targets": [
        {
          "refId": "A",
          "editorMode": "code",
          "expr": "kiosk_disk_temperature_celsius{instance=~\"$instance\"}",
          "legendFormat": "{{model}}"
        }
      ],
      "fieldConfig": {
        "defaults": {
          "unit": "celsius",
          "thresholds": {
            "mode": "absolute",
            "steps": [
              {
                "color": "green",
                "value": null
              },
              {
                "color": "orange",
                "value": 60
              },
              {
                "color": "red",
                "value": 70
              }
            ]
          }
        }
      }
    },
    {
      "id": 22,
      "type": "row",
      "title": "Thermals (CPU / GPU / fan)",
      "collapsed": false,
      "gridPos": {
        "h": 1,
        "w": 24,
        "x": 0,
        "y": 40
      }
    },
    {
      "id": 23,
      "type": "bargauge",
      "title": "CPU package temperature (°C)",
      "gridPos": {
        "h": 8,
        "w": 8,
        "x": 0,
        "y": 41
      },
      "datasource": {
        "type": "prometheus",
        "uid": "grafanacloud-prom"
      },
      "targets": [
        {
          "refId": "A",
          "editorMode": "code",
          "expr": "ohm_cpu_celsius{sensor=\"CPU Package\", instance=~\"$instance\"}",
          "instant": true,
          "legendFormat": "{{sensor}}"
        }
      ],
      "options": {
        "displayMode": "gradient",
        "orientation": "horizontal",
        "reduceOptions": {
          "calcs": [
            "lastNotNull"
          ]
        },
        "showUnfilled": true
      },
      "fieldConfig": {
        "defaults": {
          "unit": "celsius",
          "thresholds": {
            "mode": "absolute",
            "steps": [
              {
                "color": "green",
                "value": null
              },
              {
                "color": "orange",
                "value": 75
              },
              {
                "color": "red",
                "value": 90
              }
            ]
          },
          "description": "From kiosk-ohm (OhmGraphite + PawnIO). Present only on hosts with kiosk-ohm."
        }
      }
    },
    {
      "id": 24,
      "type": "bargauge",
      "title": "GPU temperature (°C)",
      "gridPos": {
        "h": 8,
        "w": 8,
        "x": 8,
        "y": 41
      },
      "datasource": {
        "type": "prometheus",
        "uid": "grafanacloud-prom"
      },
      "targets": [
        {
          "refId": "A",
          "editorMode": "code",
          "expr": "{__name__=~\"ohm_gpu.+_celsius\", instance=~\"$instance\"}",
          "instant": true,
          "legendFormat": "{{sensor}}"
        }
      ],
      "options": {
        "displayMode": "gradient",
        "orientation": "horizontal",
        "reduceOptions": {
          "calcs": [
            "lastNotNull"
          ]
        },
        "showUnfilled": true
      },
      "fieldConfig": {
        "defaults": {
          "unit": "celsius",
          "thresholds": {
            "mode": "absolute",
            "steps": [
              {
                "color": "green",
                "value": null
              },
              {
                "color": "orange",
                "value": 75
              },
              {
                "color": "red",
                "value": 90
              }
            ]
          }
        }
      }
    },
    {
      "id": 25,
      "type": "bargauge",
      "title": "GPU fan (RPM)",
      "gridPos": {
        "h": 8,
        "w": 8,
        "x": 16,
        "y": 41
      },
      "datasource": {
        "type": "prometheus",
        "uid": "grafanacloud-prom"
      },
      "targets": [
        {
          "refId": "A",
          "editorMode": "code",
          "expr": "{__name__=~\"ohm_gpu.+_revolutions_per_minute\", instance=~\"$instance\"}",
          "instant": true,
          "legendFormat": "{{sensor}}"
        }
      ],
      "options": {
        "displayMode": "gradient",
        "orientation": "horizontal",
        "reduceOptions": {
          "calcs": [
            "lastNotNull"
          ]
        },
        "showUnfilled": true
      },
      "fieldConfig": {
        "defaults": {
          "unit": "rotrpm",
          "thresholds": {
            "mode": "absolute",
            "steps": [
              {
                "color": "orange",
                "value": null
              },
              {
                "color": "orange",
                "value": 1
              }
            ]
          }
        }
      }
    },
    {
      "id": 26,
      "type": "timeseries",
      "title": "CPU / GPU temperature — trend",
      "gridPos": {
        "h": 6,
        "w": 24,
        "x": 0,
        "y": 49
      },
      "datasource": {
        "type": "prometheus",
        "uid": "grafanacloud-prom"
      },
      "targets": [
        {
          "refId": "A",
          "editorMode": "code",
          "expr": "ohm_cpu_celsius{sensor=\"CPU Package\", instance=~\"$instance\"} or {__name__=~\"ohm_gpu.+_celsius\", instance=~\"$instance\"}",
          "legendFormat": "{{__name__}} {{sensor}}"
        }
      ],
      "fieldConfig": {
        "defaults": {
          "unit": "celsius",
          "thresholds": {
            "mode": "absolute",
            "steps": [
              {
                "color": "green",
                "value": null
              },
              {
                "color": "orange",
                "value": 80
              },
              {
                "color": "red",
                "value": 90
              }
            ]
          }
        }
      }
    },
    {
      "id": 27,
      "type": "timeseries",
      "title": "GPU load %",
      "gridPos": {
        "h": 6,
        "w": 12,
        "x": 0,
        "y": 55
      },
      "datasource": {
        "type": "prometheus",
        "uid": "grafanacloud-prom"
      },
      "targets": [
        {
          "refId": "A",
          "editorMode": "code",
          "expr": "{__name__=~\"ohm_gpu.+_load_percent\", instance=~\"$instance\"}",
          "legendFormat": "{{sensor}}"
        }
      ],
      "fieldConfig": {
        "defaults": {
          "unit": "percent",
          "min": 0,
          "max": 100
        }
      }
    },
    {
      "id": 28,
      "type": "timeseries",
      "title": "GPU memory (VRAM)",
      "gridPos": {
        "h": 6,
        "w": 12,
        "x": 12,
        "y": 55
      },
      "datasource": {
        "type": "prometheus",
        "uid": "grafanacloud-prom"
      },
      "targets": [
        {
          "refId": "A",
          "editorMode": "code",
          "expr": "{__name__=~\"ohm_gpu.+_bytes\", instance=~\"$instance\"}",
          "legendFormat": "{{sensor}}"
        }
      ],
      "fieldConfig": {
        "defaults": {
          "unit": "bytes"
        }
      }
    },
    {
      "id": 29,
      "type": "row",
      "title": "Application",
      "collapsed": false,
      "gridPos": {
        "h": 1,
        "w": 24,
        "x": 0,
        "y": 61
      }
    },
    {
      "id": 30,
      "type": "timeseries",
      "title": "App memory (working set)",
      "gridPos": {
        "h": 7,
        "w": 12,
        "x": 0,
        "y": 62
      },
      "datasource": {
        "type": "prometheus",
        "uid": "grafanacloud-prom"
      },
      "targets": [
        {
          "refId": "A",
          "editorMode": "code",
          "expr": "kiosk_app_working_set_bytes{instance=~\"$instance\"}",
          "legendFormat": "{{exe}}"
        }
      ],
      "fieldConfig": {
        "defaults": {
          "unit": "bytes"
        }
      }
    },
    {
      "id": 31,
      "type": "timeseries",
      "title": "App CPU (cores)",
      "gridPos": {
        "h": 7,
        "w": 12,
        "x": 12,
        "y": 62
      },
      "datasource": {
        "type": "prometheus",
        "uid": "grafanacloud-prom"
      },
      "targets": [
        {
          "refId": "A",
          "editorMode": "code",
          "expr": "rate(kiosk_app_cpu_seconds_total{instance=~\"$instance\"}[5m])",
          "legendFormat": "{{exe}}"
        }
      ],
      "fieldConfig": {
        "defaults": {
          "unit": "short",
          "min": 0,
          "decimals": 2
        }
      }
    },
    {
      "id": 32,
      "type": "timeseries",
      "title": "App uptime",
      "gridPos": {
        "h": 7,
        "w": 12,
        "x": 0,
        "y": 69
      },
      "datasource": {
        "type": "prometheus",
        "uid": "grafanacloud-prom"
      },
      "targets": [
        {
          "refId": "A",
          "editorMode": "code",
          "expr": "time() - kiosk_app_start_time_seconds{instance=~\"$instance\"}",
          "legendFormat": "uptime"
        }
      ],
      "fieldConfig": {
        "defaults": {
          "unit": "s"
        }
      }
    },
    {
      "id": 33,
      "type": "timeseries",
      "title": "App restarts per hour",
      "gridPos": {
        "h": 7,
        "w": 12,
        "x": 12,
        "y": 69
      },
      "datasource": {
        "type": "prometheus",
        "uid": "grafanacloud-prom"
      },
      "targets": [
        {
          "refId": "A",
          "editorMode": "code",
          "expr": "changes(kiosk_app_start_time_seconds{instance=~\"$instance\"}[1h])",
          "legendFormat": "restarts/h"
        }
      ],
      "fieldConfig": {
        "defaults": {
          "unit": "short",
          "thresholds": {
            "mode": "absolute",
            "steps": [
              {
                "color": "green",
                "value": null
              },
              {
                "color": "orange",
                "value": 3
              }
            ]
          }
        }
      }
    },
    {
      "id": 34,
      "type": "row",
      "title": "Controllers & logs",
      "collapsed": false,
      "gridPos": {
        "h": 1,
        "w": 24,
        "x": 0,
        "y": 76
      }
    },
    {
      "id": 35,
      "type": "table",
      "title": "Controllers up",
      "gridPos": {
        "h": 7,
        "w": 8,
        "x": 0,
        "y": 77
      },
      "datasource": {
        "type": "prometheus",
        "uid": "grafanacloud-prom"
      },
      "targets": [
        {
          "refId": "A",
          "editorMode": "code",
          "instant": true,
          "format": "table",
          "expr": "kiosk_controller_up{instance=~\"$instance\"}"
        }
      ],
      "transformations": [
        {
          "id": "organize",
          "options": {
            "excludeByName": {
              "Time": true,
              "job": true,
              "__name__": true,
              "fleet": true,
              "host": true,
              "site": true,
              "location": true,
              "environment": true,
              "instance": true
            },
            "renameByName": {
              "Value": "up"
            }
          }
        }
      ],
      "fieldConfig": {
        "defaults": {},
        "overrides": [
          {
            "matcher": {
              "id": "byName",
              "options": "up"
            },
            "properties": [
              {
                "id": "mappings",
                "value": [
                  {
                    "type": "value",
                    "options": {
                      "0": {
                        "text": "DOWN",
                        "color": "red"
                      },
                      "1": {
                        "text": "up",
                        "color": "green"
                      }
                    }
                  }
                ]
              },
              {
                "id": "custom.cellOptions",
                "value": {
                  "type": "color-text"
                }
              }
            ]
          }
        ]
      }
    },
    {
      "id": 36,
      "type": "logs",
      "title": "Kiosk logs (agent + controllers + Windows events)",
      "gridPos": {
        "h": 7,
        "w": 16,
        "x": 8,
        "y": 77
      },
      "datasource": {
        "type": "loki",
        "uid": "grafanacloud-logs"
      },
      "targets": [
        {
          "refId": "A",
          "editorMode": "code",
          "expr": "{fleet=\"lfac\", host=~\"$instance\"} | line_format \"{{.job}} | {{__line__}}\""
        }
      ],
      "options": {
        "showTime": true,
        "wrapLogMessage": true,
        "dedupStrategy": "none",
        "sortOrder": "Descending"
      }
    }
  ]
}
